{
  "_meta_": "",
  "_sha512_": "ee6fb69f087872bba8c33373b3d9f4c881df1d46df8a01a523e1b9ac5e1f2cf0b741b80c5d4dd796ca2c491cd6d49dc83543d97f4fa408d9cf41ed160a698800",
  "dataDir": "data",
  "loadOrder": [
    "F:/Steam/steamapps/common/Skyrim Special Edition/Data/Skyrim.esm",
    "F:/Steam/steamapps/common/Skyrim Special Edition/Data/Update.esm",
    "F:/Steam/steamapps/common/Skyrim Special Edition/Data/Dawnguard.esm",
    "F:/Steam/steamapps/common/Skyrim Special Edition/Data/HearthFires.esm",
    "F:/Steam/steamapps/common/Skyrim Special Edition/Data/Dragonborn.esm"
  ],
  "master": "",
  "maxPlayers": 100,
  "name": "My Server",
  "npcEnabled": false,
  "npcSettings": {},
  "offlineMode": true,
  "port": 7777,
  "discordAuth": {
    "clientId": "1493774407951454319",
    "clientSecret": "6QdbXf6OWIU37_5Jy5dwtxVxCOoarUum"
  }
}